setup.py
LeArmPy.egg-info/PKG-INFO
LeArmPy.egg-info/SOURCES.txt
LeArmPy.egg-info/dependency_links.txt
LeArmPy.egg-info/top_level.txt
learmpy/LeArmPy.py
learmpy/__init__.py