Metadata-Version: 2.1
Name: LeArmPy
Version: 0.1
Summary: control LeArm
Home-page: https://github.com/jim0575/desktop-tutorial
Author: james
Author-email: jim0575@qq.com
License: MIT Licence
Keywords: pip,leihoo,learn
Platform: any
